{
  "kind": "collectionType",
  "collectionName": "jobs",
  "info": {
    "name": "job",
    "description": ""
  },
  "options": {
    "increments": true,
    "timestamps": true,
    "draftAndPublish": true
  },
  "pluginOptions": {},
  "attributes": {
    "name": {
      "type": "string",
      "required": true
    },
    "desc": {
      "type": "richtext"
    },
    "images": {
      "collection": "file",
      "via": "related",
      "allowedTypes": [
        "images",
        "files",
        "videos"
      ],
      "plugin": "upload",
      "required": false,
      "pluginOptions": {}
    },
    "coverImg": {
      "model": "file",
      "via": "related",
      "allowedTypes": [
        "images",
        "files",
        "videos"
      ],
      "plugin": "upload",
      "required": false,
      "pluginOptions": {}
    },
    "dateCreated": {
      "type": "date"
    },
    "wage": {
      "type": "biginteger",
      "required": true,
      "min": "0",
      "max": "1000000000"
    },
    "note": {
      "type": "richtext"
    },
    "bonus": {
      "type": "richtext"
    },
    "ratings": {
      "collection": "rating"
    }
  }
}
